ai_core/__init__.py
ai_core/test.py
ai_core/utils.py
ai_core/datasets/__init__.py
ai_core/datasets/furniture.py
ai_core/datasets/furniture_data.py
ai_core/datasets/shoes/__init__.py
ai_core/datasets/shoes/shoes.py
ai_core/datasets/shoes/shoes_init.py
ai_core/models/Autoencoder.py
ai_core/models/CNN.py
ai_core/models/NN.py
ai_core/models/TransposeCNN.py
ai_core/models/VerboseLayer.py
ai_core/models/__init__.py
ai_core/models/gans/__init__.py
ai_core/models/gans/gan.py
ai_core-0.0.14.dist-info/METADATA
ai_core-0.0.14.dist-info/WHEEL
ai_core-0.0.14.dist-info/top_level.txt
ai_core-0.0.14.dist-info/RECORD
