Metadata-Version: 2.1
Name: ai-core
Version: 0.0.14
Summary: Allows you to focus on building applications using the latest models and techniques, rather then building them yourself, by providing them in a simple API.
Home-page: https://github.com/AI-Core/ai-core
Author: Harry Berg
Author-email: harry@theaicore.com
License: MIT
Keywords: AI,ML
Platform: UNKNOWN
Requires-Dist: torch
Requires-Dist: torchvision
